ltlcross_wrapper/__init__.py
ltlcross_wrapper/analyzer.py
ltlcross_wrapper/locate_errors.py
ltlcross_wrapper/modular.py
ltlcross_wrapper/runner.py
ltlcross_wrapper/tables_utils.py
ltlcross_wrapper-0.7.3.dist-info/LICENSE
ltlcross_wrapper-0.7.3.dist-info/METADATA
ltlcross_wrapper-0.7.3.dist-info/WHEEL
ltlcross_wrapper-0.7.3.dist-info/top_level.txt
ltlcross_wrapper-0.7.3.dist-info/RECORD
