Metadata-Version: 2.1
Name: ltlcross-wrapper
Version: 0.7.3
Summary: Python wrapper around tool ltlcross from Spot library
Home-page: https://github.com/xblahoud/ltlcross_wrapper
Author: Fanda Blahoudek
Author-email: fandikb+dev@gmail.com
License: MIT
Platform: UNKNOWN
Classifier: License :: OSI Approved :: MIT License
Classifier: Programming Language :: Python :: 3
Classifier: Programming Language :: Python :: 3.6
Requires-Python: >=3.6.0
Requires-Dist: bokeh
Requires-Dist: colorcet
Requires-Dist: matplotlib
Requires-Dist: pandas2pgfplots
Requires-Dist: pandas (>=1.0.3)
Requires-Dist: seaborn
